<?xml version="1.0" encoding="UTF-8"?>
<DEFECTS>
  <DEFECT>
    <SFA>
      <FILEPATH>C:\Users\b1213\c++\HakuensaiLauncher\</FILEPATH>
      <FILENAME>Game.cpp</FILENAME>
      <LINE>116</LINE>
      <COLUMN>11</COLUMN>
    </SFA>
    <DEFECTCODE>28251</DEFECTCODE>
    <DESCRIPTION>'WinMain' に対する整合性のない注釈: このインスタンスには 注釈なし が含まれます。c:\program files (x86)\windows kits\10\include\10.0.26100.0\um\winbase.h(1062) を参照してください。</DESCRIPTION>
    <FUNCTION>WinMain</FUNCTION>
    <DECORATED>WinMain</DECORATED>
    <FUNCLINE>116</FUNCLINE>
    <PATH></PATH>
  </DEFECT>
  <DEFECT>
    <SFA>
      <FILEPATH>C:\Users\b1213\c++\HakuensaiLauncher\</FILEPATH>
      <FILENAME>Game.cpp</FILENAME>
      <LINE>640</LINE>
      <COLUMN>11</COLUMN>
    </SFA>
    <DEFECTCODE>6001</DEFECTCODE>
    <DESCRIPTION>初期化されていないメモリ 'gameeximage' を使用しています。</DESCRIPTION>
    <FUNCTION>WinMain</FUNCTION>
    <DECORATED>WinMain</DECORATED>
    <FUNCLINE>116</FUNCLINE>
    <PROBABILITY>1</PROBABILITY>
    <RANK>3</RANK>
    <CATEGORY>
      <RULECATEGORY>mspft</RULECATEGORY>
    </CATEGORY>
    <PATH>
      <SFA>
        <FILEPATH>C:\Users\b1213\c++\HakuensaiLauncher\</FILEPATH>
        <FILENAME>Game.cpp</FILENAME>
        <LINE>117</LINE>
        <COLUMN>17</COLUMN>
      </SFA>
      <SFA>
        <FILEPATH>C:\Users\b1213\c++\HakuensaiLauncher\</FILEPATH>
        <FILENAME>Game.cpp</FILENAME>
        <LINE>118</LINE>
        <COLUMN>13</COLUMN>
      </SFA>
      <SFA>
        <FILEPATH>C:\Users\b1213\c++\HakuensaiLauncher\</FILEPATH>
        <FILENAME>Game.cpp</FILENAME>
        <LINE>119</LINE>
        <COLUMN>18</COLUMN>
      </SFA>
      <SFA>
        <FILEPATH>C:\Users\b1213\c++\HakuensaiLauncher\</FILEPATH>
        <FILENAME>Game.cpp</FILENAME>
        <LINE>120</LINE>
        <COLUMN>17</COLUMN>
      </SFA>
      <SFA>
        <FILEPATH>C:\Users\b1213\c++\HakuensaiLauncher\</FILEPATH>
        <FILENAME>Game.cpp</FILENAME>
        <LINE>121</LINE>
        <COLUMN>19</COLUMN>
      </SFA>
      <SFA>
        <FILEPATH>C:\Users\b1213\c++\HakuensaiLauncher\</FILEPATH>
        <FILENAME>Game.cpp</FILENAME>
        <LINE>122</LINE>
        <COLUMN>19</COLUMN>
      </SFA>
      <SFA>
        <FILEPATH>C:\Users\b1213\c++\HakuensaiLauncher\</FILEPATH>
        <FILENAME>Game.cpp</FILENAME>
        <LINE>123</LINE>
        <COLUMN>24</COLUMN>
      </SFA>
      <SFA>
        <FILEPATH>C:\Users\b1213\c++\HakuensaiLauncher\</FILEPATH>
        <FILENAME>Game.cpp</FILENAME>
        <LINE>124</LINE>
        <COLUMN>22</COLUMN>
      </SFA>
      <SFA>
        <FILEPATH>C:\Users\b1213\c++\HakuensaiLauncher\</FILEPATH>
        <FILENAME>Game.cpp</FILENAME>
        <LINE>125</LINE>
        <COLUMN>18</COLUMN>
      </SFA>
      <SFA>
        <FILEPATH>C:\Users\b1213\c++\HakuensaiLauncher\</FILEPATH>
        <FILENAME>Game.cpp</FILENAME>
        <LINE>127</LINE>
        <COLUMN>15</COLUMN>
      </SFA>
      <SFA>
        <FILEPATH>C:\Users\b1213\c++\HakuensaiLauncher\</FILEPATH>
        <FILENAME>Game.cpp</FILENAME>
        <LINE>128</LINE>
        <COLUMN>12</COLUMN>
      </SFA>
      <SFA>
        <FILEPATH>C:\Users\b1213\c++\HakuensaiLauncher\</FILEPATH>
        <FILENAME>Game.cpp</FILENAME>
        <LINE>129</LINE>
        <COLUMN>6</COLUMN>
      </SFA>
      <SFA>
        <FILEPATH>C:\Users\b1213\c++\HakuensaiLauncher\</FILEPATH>
        <FILENAME>Game.cpp</FILENAME>
        <LINE>130</LINE>
        <COLUMN>14</COLUMN>
      </SFA>
      <SFA>
        <FILEPATH>C:\Users\b1213\c++\HakuensaiLauncher\</FILEPATH>
        <FILENAME>Game.cpp</FILENAME>
        <LINE>131</LINE>
        <COLUMN>12</COLUMN>
      </SFA>
      <SFA>
        <FILEPATH>C:\Users\b1213\c++\HakuensaiLauncher\</FILEPATH>
        <FILENAME>Game.cpp</FILENAME>
        <LINE>132</LINE>
        <COLUMN>12</COLUMN>
      </SFA>
      <SFA>
        <FILEPATH>C:\Users\b1213\c++\HakuensaiLauncher\</FILEPATH>
        <FILENAME>Game.cpp</FILENAME>
        <LINE>133</LINE>
        <COLUMN>12</COLUMN>
      </SFA>
      <SFA>
        <FILEPATH>C:\Users\b1213\c++\HakuensaiLauncher\</FILEPATH>
        <FILENAME>Game.cpp</FILENAME>
        <LINE>134</LINE>
        <COLUMN>12</COLUMN>
      </SFA>
      <SFA>
        <FILEPATH>C:\Users\b1213\c++\HakuensaiLauncher\</FILEPATH>
        <FILENAME>Game.cpp</FILENAME>
        <LINE>135</LINE>
        <COLUMN>14</COLUMN>
      </SFA>
      <SFA>
        <FILEPATH>C:\Users\b1213\c++\HakuensaiLauncher\</FILEPATH>
        <FILENAME>Game.cpp</FILENAME>
        <LINE>136</LINE>
        <COLUMN>12</COLUMN>
      </SFA>
      <SFA>
        <FILEPATH>C:\Users\b1213\c++\HakuensaiLauncher\</FILEPATH>
        <FILENAME>Game.cpp</FILENAME>
        <LINE>137</LINE>
        <COLUMN>5</COLUMN>
      </SFA>
      <SFA>
        <FILEPATH>C:\Users\b1213\c++\HakuensaiLauncher\</FILEPATH>
        <FILENAME>Game.cpp</FILENAME>
        <LINE>138</LINE>
        <COLUMN>12</COLUMN>
      </SFA>
      <SFA>
        <FILEPATH>C:\Users\b1213\c++\HakuensaiLauncher\</FILEPATH>
        <FILENAME>Game.cpp</FILENAME>
        <LINE>139</LINE>
        <COLUMN>8</COLUMN>
      </SFA>
      <SFA>
        <FILEPATH>C:\Users\b1213\c++\HakuensaiLauncher\</FILEPATH>
        <FILENAME>Game.cpp</FILENAME>
        <LINE>140</LINE>
        <COLUMN>19</COLUMN>
      </SFA>
      <SFA>
        <FILEPATH>C:\Users\b1213\c++\HakuensaiLauncher\</FILEPATH>
        <FILENAME>Game.cpp</FILENAME>
        <LINE>141</LINE>
        <COLUMN>11</COLUMN>
      </SFA>
      <SFA>
        <FILEPATH>C:\Users\b1213\c++\HakuensaiLauncher\</FILEPATH>
        <FILENAME>Game.cpp</FILENAME>
        <LINE>142</LINE>
        <COLUMN>5</COLUMN>
      </SFA>
      <SFA>
        <FILEPATH>C:\Users\b1213\c++\HakuensaiLauncher\</FILEPATH>
        <FILENAME>Game.cpp</FILENAME>
        <LINE>143</LINE>
        <COLUMN>12</COLUMN>
      </SFA>
      <SFA>
        <FILEPATH>C:\Users\b1213\c++\HakuensaiLauncher\</FILEPATH>
        <FILENAME>Game.cpp</FILENAME>
        <LINE>144</LINE>
        <COLUMN>16</COLUMN>
      </SFA>
      <SFA>
        <FILEPATH>C:\Users\b1213\c++\HakuensaiLauncher\</FILEPATH>
        <FILENAME>Game.cpp</FILENAME>
        <LINE>145</LINE>
        <COLUMN>8</COLUMN>
      </SFA>
      <SFA>
        <FILEPATH>C:\Users\b1213\c++\HakuensaiLauncher\</FILEPATH>
        <FILENAME>Game.cpp</FILENAME>
        <LINE>146</LINE>
        <COLUMN>19</COLUMN>
      </SFA>
      <SFA>
        <FILEPATH>C:\Users\b1213\c++\HakuensaiLauncher\</FILEPATH>
        <FILENAME>Game.cpp</FILENAME>
        <LINE>147</LINE>
        <COLUMN>11</COLUMN>
      </SFA>
      <SFA>
        <FILEPATH>C:\Users\b1213\c++\HakuensaiLauncher\</FILEPATH>
        <FILENAME>Game.cpp</FILENAME>
        <LINE>148</LINE>
        <COLUMN>5</COLUMN>
      </SFA>
      <SFA>
        <FILEPATH>C:\Users\b1213\c++\HakuensaiLauncher\</FILEPATH>
        <FILENAME>Game.cpp</FILENAME>
        <LINE>149</LINE>
        <COLUMN>12</COLUMN>
      </SFA>
      <SFA>
        <FILEPATH>C:\Users\b1213\c++\HakuensaiLauncher\</FILEPATH>
        <FILENAME>Game.cpp</FILENAME>
        <LINE>150</LINE>
        <COLUMN>16</COLUMN>
      </SFA>
      <SFA>
        <FILEPATH>C:\Users\b1213\c++\HakuensaiLauncher\</FILEPATH>
        <FILENAME>Game.cpp</FILENAME>
        <LINE>151</LINE>
        <COLUMN>8</COLUMN>
      </SFA>
      <SFA>
        <FILEPATH>C:\Users\b1213\c++\HakuensaiLauncher\</FILEPATH>
        <FILENAME>Game.cpp</FILENAME>
        <LINE>152</LINE>
        <COLUMN>19</COLUMN>
      </SFA>
      <SFA>
        <FILEPATH>C:\Users\b1213\c++\HakuensaiLauncher\</FILEPATH>
        <FILENAME>Game.cpp</FILENAME>
        <LINE>153</LINE>
        <COLUMN>11</COLUMN>
      </SFA>
      <SFA>
        <FILEPATH>C:\Users\b1213\c++\HakuensaiLauncher\</FILEPATH>
        <FILENAME>Game.cpp</FILENAME>
        <LINE>154</LINE>
        <COLUMN>5</COLUMN>
      </SFA>
      <SFA>
        <FILEPATH>C:\Users\b1213\c++\HakuensaiLauncher\</FILEPATH>
        <FILENAME>Game.cpp</FILENAME>
        <LINE>155</LINE>
        <COLUMN>12</COLUMN>
      </SFA>
      <SFA>
        <FILEPATH>C:\Users\b1213\c++\HakuensaiLauncher\</FILEPATH>
        <FILENAME>Game.cpp</FILENAME>
        <LINE>156</LINE>
        <COLUMN>16</COLUMN>
      </SFA>
      <SFA>
        <FILEPATH>C:\Users\b1213\c++\HakuensaiLauncher\</FILEPATH>
        <FILENAME>Game.cpp</FILENAME>
        <LINE>157</LINE>
        <COLUMN>8</COLUMN>
      </SFA>
      <SFA>
        <FILEPATH>C:\Users\b1213\c++\HakuensaiLauncher\</FILEPATH>
        <FILENAME>Game.cpp</FILENAME>
        <LINE>158</LINE>
        <COLUMN>19</COLUMN>
      </SFA>
      <SFA>
        <FILEPATH>C:\Users\b1213\c++\HakuensaiLauncher\</FILEPATH>
        <FILENAME>Game.cpp</FILENAME>
        <LINE>159</LINE>
        <COLUMN>11</COLUMN>
      </SFA>
      <SFA>
        <FILEPATH>C:\Users\b1213\c++\HakuensaiLauncher\</FILEPATH>
        <FILENAME>Game.cpp</FILENAME>
        <LINE>160</LINE>
        <COLUMN>8</COLUMN>
      </SFA>
      <SFA>
        <FILEPATH>C:\Users\b1213\c++\HakuensaiLauncher\</FILEPATH>
        <FILENAME>Game.cpp</FILENAME>
        <LINE>161</LINE>
        <COLUMN>12</COLUMN>
      </SFA>
      <SFA>
        <FILEPATH>C:\Users\b1213\c++\HakuensaiLauncher\</FILEPATH>
        <FILENAME>Game.cpp</FILENAME>
        <LINE>162</LINE>
        <COLUMN>16</COLUMN>
      </SFA>
      <SFA>
        <FILEPATH>C:\Users\b1213\c++\HakuensaiLauncher\</FILEPATH>
        <FILENAME>Game.cpp</FILENAME>
        <LINE>163</LINE>
        <COLUMN>8</COLUMN>
      </SFA>
      <SFA>
        <FILEPATH>C:\Users\b1213\c++\HakuensaiLauncher\</FILEPATH>
        <FILENAME>Game.cpp</FILENAME>
        <LINE>164</LINE>
        <COLUMN>19</COLUMN>
      </SFA>
      <SFA>
        <FILEPATH>C:\Users\b1213\c++\HakuensaiLauncher\</FILEPATH>
        <FILENAME>Game.cpp</FILENAME>
        <LINE>165</LINE>
        <COLUMN>11</COLUMN>
      </SFA>
      <SFA>
        <FILEPATH>C:\Users\b1213\c++\HakuensaiLauncher\</FILEPATH>
        <FILENAME>Game.cpp</FILENAME>
        <LINE>166</LINE>
        <COLUMN>5</COLUMN>
      </SFA>
      <SFA>
        <FILEPATH>C:\Users\b1213\c++\HakuensaiLauncher\</FILEPATH>
        <FILENAME>Game.cpp</FILENAME>
        <LINE>167</LINE>
        <COLUMN>12</COLUMN>
      </SFA>
      <SFA>
        <FILEPATH>C:\Users\b1213\c++\HakuensaiLauncher\</FILEPATH>
        <FILENAME>Game.cpp</FILENAME>
        <LINE>168</LINE>
        <COLUMN>16</COLUMN>
      </SFA>
      <SFA>
        <FILEPATH>C:\Users\b1213\c++\HakuensaiLauncher\</FILEPATH>
        <FILENAME>Game.cpp</FILENAME>
        <LINE>169</LINE>
        <COLUMN>8</COLUMN>
      </SFA>
      <SFA>
        <FILEPATH>C:\Users\b1213\c++\HakuensaiLauncher\</FILEPATH>
        <FILENAME>Game.cpp</FILENAME>
        <LINE>170</LINE>
        <COLUMN>19</COLUMN>
      </SFA>
      <SFA>
        <FILEPATH>C:\Users\b1213\c++\HakuensaiLauncher\</FILEPATH>
        <FILENAME>Game.cpp</FILENAME>
        <LINE>171</LINE>
        <COLUMN>11</COLUMN>
      </SFA>
      <SFA>
        <FILEPATH>C:\Users\b1213\c++\HakuensaiLauncher\</FILEPATH>
        <FILENAME>Game.cpp</FILENAME>
        <LINE>172</LINE>
        <COLUMN>5</COLUMN>
      </SFA>
      <SFA>
        <FILEPATH>C:\Users\b1213\c++\HakuensaiLauncher\</FILEPATH>
        <FILENAME>Game.cpp</FILENAME>
        <LINE>173</LINE>
        <COLUMN>12</COLUMN>
      </SFA>
      <SFA>
        <FILEPATH>C:\Users\b1213\c++\HakuensaiLauncher\</FILEPATH>
        <FILENAME>Game.cpp</FILENAME>
        <LINE>174</LINE>
        <COLUMN>16</COLUMN>
      </SFA>
      <SFA>
        <FILEPATH>C:\Users\b1213\c++\HakuensaiLauncher\</FILEPATH>
        <FILENAME>Game.cpp</FILENAME>
        <LINE>175</LINE>
        <COLUMN>8</COLUMN>
      </SFA>
      <SFA>
        <FILEPATH>C:\Users\b1213\c++\HakuensaiLauncher\</FILEPATH>
        <FILENAME>Game.cpp</FILENAME>
        <LINE>176</LINE>
        <COLUMN>19</COLUMN>
      </SFA>
      <SFA>
        <FILEPATH>C:\Users\b1213\c++\HakuensaiLauncher\</FILEPATH>
        <FILENAME>Game.cpp</FILENAME>
        <LINE>177</LINE>
        <COLUMN>11</COLUMN>
      </SFA>
      <SFA>
        <FILEPATH>C:\Users\b1213\c++\HakuensaiLauncher\</FILEPATH>
        <FILENAME>Game.cpp</FILENAME>
        <LINE>178</LINE>
        <COLUMN>5</COLUMN>
      </SFA>
      <SFA>
        <FILEPATH>C:\Users\b1213\c++\HakuensaiLauncher\</FILEPATH>
        <FILENAME>Game.cpp</FILENAME>
        <LINE>178</LINE>
        <COLUMN>13</COLUMN>
      </SFA>
      <SFA>
        <FILEPATH>C:\Users\b1213\c++\HakuensaiLauncher\</FILEPATH>
        <FILENAME>Game.cpp</FILENAME>
        <LINE>179</LINE>
        <COLUMN>12</COLUMN>
      </SFA>
      <SFA>
        <FILEPATH>C:\Users\b1213\c++\HakuensaiLauncher\</FILEPATH>
        <FILENAME>Game.cpp</FILENAME>
        <LINE>180</LINE>
        <COLUMN>16</COLUMN>
      </SFA>
      <SFA>
        <FILEPATH>C:\Users\b1213\c++\HakuensaiLauncher\</FILEPATH>
        <FILENAME>Game.cpp</FILENAME>
        <LINE>181</LINE>
        <COLUMN>8</COLUMN>
      </SFA>
      <SFA>
        <FILEPATH>C:\Users\b1213\c++\HakuensaiLauncher\</FILEPATH>
        <FILENAME>Game.cpp</FILENAME>
        <LINE>182</LINE>
        <COLUMN>19</COLUMN>
      </SFA>
      <SFA>
        <FILEPATH>C:\Users\b1213\c++\HakuensaiLauncher\</FILEPATH>
        <FILENAME>Game.cpp</FILENAME>
        <LINE>183</LINE>
        <COLUMN>11</COLUMN>
      </SFA>
      <SFA>
        <FILEPATH>C:\Users\b1213\c++\HakuensaiLauncher\</FILEPATH>
        <FILENAME>Game.cpp</FILENAME>
        <LINE>184</LINE>
        <COLUMN>5</COLUMN>
      </SFA>
      <SFA>
        <FILEPATH>C:\Users\b1213\c++\HakuensaiLauncher\</FILEPATH>
        <FILENAME>Game.cpp</FILENAME>
        <LINE>185</LINE>
        <COLUMN>12</COLUMN>
      </SFA>
      <SFA>
        <FILEPATH>C:\Users\b1213\c++\HakuensaiLauncher\</FILEPATH>
        <FILENAME>Game.cpp</FILENAME>
        <LINE>186</LINE>
        <COLUMN>16</COLUMN>
      </SFA>
      <SFA>
        <FILEPATH>C:\Users\b1213\c++\HakuensaiLauncher\</FILEPATH>
        <FILENAME>Game.cpp</FILENAME>
        <LINE>187</LINE>
        <COLUMN>8</COLUMN>
      </SFA>
      <SFA>
        <FILEPATH>C:\Users\b1213\c++\HakuensaiLauncher\</FILEPATH>
        <FILENAME>Game.cpp</FILENAME>
        <LINE>188</LINE>
        <COLUMN>19</COLUMN>
      </SFA>
      <SFA>
        <FILEPATH>C:\Users\b1213\c++\HakuensaiLauncher\</FILEPATH>
        <FILENAME>Game.cpp</FILENAME>
        <LINE>189</LINE>
        <COLUMN>11</COLUMN>
      </SFA>
      <SFA>
        <FILEPATH>C:\Users\b1213\c++\HakuensaiLauncher\</FILEPATH>
        <FILENAME>Game.cpp</FILENAME>
        <LINE>190</LINE>
        <COLUMN>5</COLUMN>
      </SFA>
      <SFA>
        <FILEPATH>C:\Users\b1213\c++\HakuensaiLauncher\</FILEPATH>
        <FILENAME>Game.cpp</FILENAME>
        <LINE>191</LINE>
        <COLUMN>12</COLUMN>
      </SFA>
      <SFA>
        <FILEPATH>C:\Users\b1213\c++\HakuensaiLauncher\</FILEPATH>
        <FILENAME>Game.cpp</FILENAME>
        <LINE>192</LINE>
        <COLUMN>16</COLUMN>
      </SFA>
      <SFA>
        <FILEPATH>C:\Users\b1213\c++\HakuensaiLauncher\</FILEPATH>
        <FILENAME>Game.cpp</FILENAME>
        <LINE>193</LINE>
        <COLUMN>8</COLUMN>
      </SFA>
      <SFA>
        <FILEPATH>C:\Users\b1213\c++\HakuensaiLauncher\</FILEPATH>
        <FILENAME>Game.cpp</FILENAME>
        <LINE>194</LINE>
        <COLUMN>19</COLUMN>
      </SFA>
      <SFA>
        <FILEPATH>C:\Users\b1213\c++\HakuensaiLauncher\</FILEPATH>
        <FILENAME>Game.cpp</FILENAME>
        <LINE>195</LINE>
        <COLUMN>11</COLUMN>
      </SFA>
      <SFA>
        <FILEPATH>C:\Users\b1213\c++\HakuensaiLauncher\</FILEPATH>
        <FILENAME>Game.cpp</FILENAME>
        <LINE>196</LINE>
        <COLUMN>5</COLUMN>
      </SFA>
      <SFA>
        <FILEPATH>C:\Users\b1213\c++\HakuensaiLauncher\</FILEPATH>
        <FILENAME>Game.cpp</FILENAME>
        <LINE>197</LINE>
        <COLUMN>12</COLUMN>
      </SFA>
      <SFA>
        <FILEPATH>C:\Users\b1213\c++\HakuensaiLauncher\</FILEPATH>
        <FILENAME>Game.cpp</FILENAME>
        <LINE>198</LINE>
        <COLUMN>16</COLUMN>
      </SFA>
      <SFA>
        <FILEPATH>C:\Users\b1213\c++\HakuensaiLauncher\</FILEPATH>
        <FILENAME>Game.cpp</FILENAME>
        <LINE>199</LINE>
        <COLUMN>8</COLUMN>
      </SFA>
      <SFA>
        <FILEPATH>C:\Users\b1213\c++\HakuensaiLauncher\</FILEPATH>
        <FILENAME>Game.cpp</FILENAME>
        <LINE>200</LINE>
        <COLUMN>19</COLUMN>
      </SFA>
      <SFA>
        <FILEPATH>C:\Users\b1213\c++\HakuensaiLauncher\</FILEPATH>
        <FILENAME>Game.cpp</FILENAME>
        <LINE>201</LINE>
        <COLUMN>11</COLUMN>
      </SFA>
      <SFA>
        <FILEPATH>C:\Users\b1213\c++\HakuensaiLauncher\</FILEPATH>
        <FILENAME>Game.cpp</FILENAME>
        <LINE>202</LINE>
        <COLUMN>5</COLUMN>
      </SFA>
      <SFA>
        <FILEPATH>C:\Users\b1213\c++\HakuensaiLauncher\</FILEPATH>
        <FILENAME>Game.cpp</FILENAME>
        <LINE>203</LINE>
        <COLUMN>12</COLUMN>
      </SFA>
      <SFA>
        <FILEPATH>C:\Users\b1213\c++\HakuensaiLauncher\</FILEPATH>
        <FILENAME>Game.cpp</FILENAME>
        <LINE>204</LINE>
        <COLUMN>16</COLUMN>
      </SFA>
      <SFA>
        <FILEPATH>C:\Users\b1213\c++\HakuensaiLauncher\</FILEPATH>
        <FILENAME>Game.cpp</FILENAME>
        <LINE>205</LINE>
        <COLUMN>8</COLUMN>
      </SFA>
      <SFA>
        <FILEPATH>C:\Users\b1213\c++\HakuensaiLauncher\</FILEPATH>
        <FILENAME>Game.cpp</FILENAME>
        <LINE>206</LINE>
        <COLUMN>19</COLUMN>
      </SFA>
      <SFA>
        <FILEPATH>C:\Users\b1213\c++\HakuensaiLauncher\</FILEPATH>
        <FILENAME>Game.cpp</FILENAME>
        <LINE>207</LINE>
        <COLUMN>11</COLUMN>
      </SFA>
      <SFA>
        <FILEPATH>C:\Users\b1213\c++\HakuensaiLauncher\</FILEPATH>
        <FILENAME>Game.cpp</FILENAME>
        <LINE>208</LINE>
        <COLUMN>5</COLUMN>
      </SFA>
      <SFA>
        <FILEPATH>C:\Users\b1213\c++\HakuensaiLauncher\</FILEPATH>
        <FILENAME>Game.cpp</FILENAME>
        <LINE>209</LINE>
        <COLUMN>12</COLUMN>
      </SFA>
      <SFA>
        <FILEPATH>C:\Users\b1213\c++\HakuensaiLauncher\</FILEPATH>
        <FILENAME>Game.cpp</FILENAME>
        <LINE>210</LINE>
        <COLUMN>16</COLUMN>
      </SFA>
      <SFA>
        <FILEPATH>C:\Users\b1213\c++\HakuensaiLauncher\</FILEPATH>
        <FILENAME>Game.cpp</FILENAME>
        <LINE>211</LINE>
        <COLUMN>8</COLUMN>
      </SFA>
      <SFA>
        <FILEPATH>C:\Users\b1213\c++\HakuensaiLauncher\</FILEPATH>
        <FILENAME>Game.cpp</FILENAME>
        <LINE>212</LINE>
        <COLUMN>19</COLUMN>
      </SFA>
      <SFA>
        <FILEPATH>C:\Users\b1213\c++\HakuensaiLauncher\</FILEPATH>
        <FILENAME>Game.cpp</FILENAME>
        <LINE>213</LINE>
        <COLUMN>11</COLUMN>
      </SFA>
      <SFA>
        <FILEPATH>C:\Users\b1213\c++\HakuensaiLauncher\</FILEPATH>
        <FILENAME>Game.cpp</FILENAME>
        <LINE>214</LINE>
        <COLUMN>5</COLUMN>
      </SFA>
      <SFA>
        <FILEPATH>C:\Users\b1213\c++\HakuensaiLauncher\</FILEPATH>
        <FILENAME>Game.cpp</FILENAME>
        <LINE>215</LINE>
        <COLUMN>12</COLUMN>
      </SFA>
      <SFA>
        <FILEPATH>C:\Users\b1213\c++\HakuensaiLauncher\</FILEPATH>
        <FILENAME>Game.cpp</FILENAME>
        <LINE>216</LINE>
        <COLUMN>16</COLUMN>
      </SFA>
      <SFA>
        <FILEPATH>C:\Users\b1213\c++\HakuensaiLauncher\</FILEPATH>
        <FILENAME>Game.cpp</FILENAME>
        <LINE>217</LINE>
        <COLUMN>8</COLUMN>
      </SFA>
      <SFA>
        <FILEPATH>C:\Users\b1213\c++\HakuensaiLauncher\</FILEPATH>
        <FILENAME>Game.cpp</FILENAME>
        <LINE>218</LINE>
        <COLUMN>19</COLUMN>
      </SFA>
      <SFA>
        <FILEPATH>C:\Users\b1213\c++\HakuensaiLauncher\</FILEPATH>
        <FILENAME>Game.cpp</FILENAME>
        <LINE>219</LINE>
        <COLUMN>11</COLUMN>
      </SFA>
      <SFA>
        <FILEPATH>C:\Users\b1213\c++\HakuensaiLauncher\</FILEPATH>
        <FILENAME>Game.cpp</FILENAME>
        <LINE>220</LINE>
        <COLUMN>11</COLUMN>
      </SFA>
      <SFA>
        <FILEPATH>C:\Users\b1213\c++\HakuensaiLauncher\</FILEPATH>
        <FILENAME>Game.cpp</FILENAME>
        <LINE>221</LINE>
        <COLUMN>12</COLUMN>
      </SFA>
      <SFA>
        <FILEPATH>C:\Users\b1213\c++\HakuensaiLauncher\</FILEPATH>
        <FILENAME>Game.cpp</FILENAME>
        <LINE>222</LINE>
        <COLUMN>16</COLUMN>
      </SFA>
      <SFA>
        <FILEPATH>C:\Users\b1213\c++\HakuensaiLauncher\</FILEPATH>
        <FILENAME>Game.cpp</FILENAME>
        <LINE>223</LINE>
        <COLUMN>8</COLUMN>
      </SFA>
      <SFA>
        <FILEPATH>C:\Users\b1213\c++\HakuensaiLauncher\</FILEPATH>
        <FILENAME>Game.cpp</FILENAME>
        <LINE>224</LINE>
        <COLUMN>19</COLUMN>
      </SFA>
      <SFA>
        <FILEPATH>C:\Users\b1213\c++\HakuensaiLauncher\</FILEPATH>
        <FILENAME>Game.cpp</FILENAME>
        <LINE>225</LINE>
        <COLUMN>11</COLUMN>
      </SFA>
      <SFA>
        <FILEPATH>C:\Users\b1213\c++\HakuensaiLauncher\</FILEPATH>
        <FILENAME>Game.cpp</FILENAME>
        <LINE>226</LINE>
        <COLUMN>6</COLUMN>
      </SFA>
      <SFA>
        <FILEPATH>C:\Users\b1213\c++\HakuensaiLauncher\</FILEPATH>
        <FILENAME>Game.cpp</FILENAME>
        <LINE>227</LINE>
        <COLUMN>12</COLUMN>
      </SFA>
      <SFA>
        <FILEPATH>C:\Users\b1213\c++\HakuensaiLauncher\</FILEPATH>
        <FILENAME>Game.cpp</FILENAME>
        <LINE>228</LINE>
        <COLUMN>16</COLUMN>
      </SFA>
      <SFA>
        <FILEPATH>C:\Users\b1213\c++\HakuensaiLauncher\</FILEPATH>
        <FILENAME>Game.cpp</FILENAME>
        <LINE>229</LINE>
        <COLUMN>8</COLUMN>
      </SFA>
      <SFA>
        <FILEPATH>C:\Users\b1213\c++\HakuensaiLauncher\</FILEPATH>
        <FILENAME>Game.cpp</FILENAME>
        <LINE>230</LINE>
        <COLUMN>19</COLUMN>
      </SFA>
      <SFA>
        <FILEPATH>C:\Users\b1213\c++\HakuensaiLauncher\</FILEPATH>
        <FILENAME>Game.cpp</FILENAME>
        <LINE>231</LINE>
        <COLUMN>11</COLUMN>
      </SFA>
      <SFA>
        <FILEPATH>C:\Users\b1213\c++\HakuensaiLauncher\</FILEPATH>
        <FILENAME>Game.cpp</FILENAME>
        <LINE>232</LINE>
        <COLUMN>21</COLUMN>
      </SFA>
      <SFA>
        <FILEPATH>C:\Users\b1213\c++\HakuensaiLauncher\</FILEPATH>
        <FILENAME>Game.cpp</FILENAME>
        <LINE>233</LINE>
        <COLUMN>12</COLUMN>
      </SFA>
      <SFA>
        <FILEPATH>C:\Users\b1213\c++\HakuensaiLauncher\</FILEPATH>
        <FILENAME>Game.cpp</FILENAME>
        <LINE>234</LINE>
        <COLUMN>16</COLUMN>
      </SFA>
      <SFA>
        <FILEPATH>C:\Users\b1213\c++\HakuensaiLauncher\</FILEPATH>
        <FILENAME>Game.cpp</FILENAME>
        <LINE>235</LINE>
        <COLUMN>8</COLUMN>
      </SFA>
      <SFA>
        <FILEPATH>C:\Users\b1213\c++\HakuensaiLauncher\</FILEPATH>
        <FILENAME>Game.cpp</FILENAME>
        <LINE>236</LINE>
        <COLUMN>19</COLUMN>
      </SFA>
      <SFA>
        <FILEPATH>C:\Users\b1213\c++\HakuensaiLauncher\</FILEPATH>
        <FILENAME>Game.cpp</FILENAME>
        <LINE>237</LINE>
        <COLUMN>11</COLUMN>
      </SFA>
      <SFA>
        <FILEPATH>C:\Users\b1213\c++\HakuensaiLauncher\</FILEPATH>
        <FILENAME>Game.cpp</FILENAME>
        <LINE>238</LINE>
        <COLUMN>5</COLUMN>
      </SFA>
      <SFA>
        <FILEPATH>C:\Users\b1213\c++\HakuensaiLauncher\</FILEPATH>
        <FILENAME>Game.cpp</FILENAME>
        <LINE>239</LINE>
        <COLUMN>12</COLUMN>
      </SFA>
      <SFA>
        <FILEPATH>C:\Users\b1213\c++\HakuensaiLauncher\</FILEPATH>
        <FILENAME>Game.cpp</FILENAME>
        <LINE>240</LINE>
        <COLUMN>16</COLUMN>
      </SFA>
      <SFA>
        <FILEPATH>C:\Users\b1213\c++\HakuensaiLauncher\</FILEPATH>
        <FILENAME>Game.cpp</FILENAME>
        <LINE>241</LINE>
        <COLUMN>8</COLUMN>
      </SFA>
      <SFA>
        <FILEPATH>C:\Users\b1213\c++\HakuensaiLauncher\</FILEPATH>
        <FILENAME>Game.cpp</FILENAME>
        <LINE>242</LINE>
        <COLUMN>19</COLUMN>
      </SFA>
      <SFA>
        <FILEPATH>C:\Users\b1213\c++\HakuensaiLauncher\</FILEPATH>
        <FILENAME>Game.cpp</FILENAME>
        <LINE>243</LINE>
        <COLUMN>11</COLUMN>
      </SFA>
      <SFA>
        <FILEPATH>C:\Users\b1213\c++\HakuensaiLauncher\</FILEPATH>
        <FILENAME>Game.cpp</FILENAME>
        <LINE>244</LINE>
        <COLUMN>5</COLUMN>
      </SFA>
      <SFA>
        <FILEPATH>C:\Users\b1213\c++\HakuensaiLauncher\</FILEPATH>
        <FILENAME>Game.cpp</FILENAME>
        <LINE>245</LINE>
        <COLUMN>12</COLUMN>
      </SFA>
      <SFA>
        <FILEPATH>C:\Users\b1213\c++\HakuensaiLauncher\</FILEPATH>
        <FILENAME>Game.cpp</FILENAME>
        <LINE>246</LINE>
        <COLUMN>16</COLUMN>
      </SFA>
      <SFA>
        <FILEPATH>C:\Users\b1213\c++\HakuensaiLauncher\</FILEPATH>
        <FILENAME>Game.cpp</FILENAME>
        <LINE>247</LINE>
        <COLUMN>8</COLUMN>
      </SFA>
      <SFA>
        <FILEPATH>C:\Users\b1213\c++\HakuensaiLauncher\</FILEPATH>
        <FILENAME>Game.cpp</FILENAME>
        <LINE>248</LINE>
        <COLUMN>19</COLUMN>
      </SFA>
      <SFA>
        <FILEPATH>C:\Users\b1213\c++\HakuensaiLauncher\</FILEPATH>
        <FILENAME>Game.cpp</FILENAME>
        <LINE>249</LINE>
        <COLUMN>11</COLUMN>
      </SFA>
      <SFA>
        <FILEPATH>C:\Users\b1213\c++\HakuensaiLauncher\</FILEPATH>
        <FILENAME>Game.cpp</FILENAME>
        <LINE>250</LINE>
        <COLUMN>5</COLUMN>
      </SFA>
      <SFA>
        <FILEPATH>C:\Users\b1213\c++\HakuensaiLauncher\</FILEPATH>
        <FILENAME>Game.cpp</FILENAME>
        <LINE>251</LINE>
        <COLUMN>12</COLUMN>
      </SFA>
      <SFA>
        <FILEPATH>C:\Users\b1213\c++\HakuensaiLauncher\</FILEPATH>
        <FILENAME>Game.cpp</FILENAME>
        <LINE>252</LINE>
        <COLUMN>16</COLUMN>
      </SFA>
      <SFA>
        <FILEPATH>C:\Users\b1213\c++\HakuensaiLauncher\</FILEPATH>
        <FILENAME>Game.cpp</FILENAME>
        <LINE>253</LINE>
        <COLUMN>8</COLUMN>
      </SFA>
      <SFA>
        <FILEPATH>C:\Users\b1213\c++\HakuensaiLauncher\</FILEPATH>
        <FILENAME>Game.cpp</FILENAME>
        <LINE>254</LINE>
        <COLUMN>19</COLUMN>
      </SFA>
      <SFA>
        <FILEPATH>C:\Users\b1213\c++\HakuensaiLauncher\</FILEPATH>
        <FILENAME>Game.cpp</FILENAME>
        <LINE>255</LINE>
        <COLUMN>11</COLUMN>
      </SFA>
      <SFA>
        <FILEPATH>C:\Users\b1213\c++\HakuensaiLauncher\</FILEPATH>
        <FILENAME>Game.cpp</FILENAME>
        <LINE>256</LINE>
        <COLUMN>5</COLUMN>
      </SFA>
      <SFA>
        <FILEPATH>C:\Users\b1213\c++\HakuensaiLauncher\</FILEPATH>
        <FILENAME>Game.cpp</FILENAME>
        <LINE>257</LINE>
        <COLUMN>12</COLUMN>
      </SFA>
      <SFA>
        <FILEPATH>C:\Users\b1213\c++\HakuensaiLauncher\</FILEPATH>
        <FILENAME>Game.cpp</FILENAME>
        <LINE>258</LINE>
        <COLUMN>14</COLUMN>
      </SFA>
      <SFA>
        <FILEPATH>C:\Users\b1213\c++\HakuensaiLauncher\</FILEPATH>
        <FILENAME>Game.cpp</FILENAME>
        <LINE>259</LINE>
        <COLUMN>12</COLUMN>
      </SFA>
      <SFA>
        <FILEPATH>C:\Users\b1213\c++\HakuensaiLauncher\</FILEPATH>
        <FILENAME>Game.cpp</FILENAME>
        <LINE>260</LINE>
        <COLUMN>6</COLUMN>
      </SFA>
      <SFA>
        <FILEPATH>C:\Users\b1213\c++\HakuensaiLauncher\</FILEPATH>
        <FILENAME>Game.cpp</FILENAME>
        <LINE>261</LINE>
        <COLUMN>12</COLUMN>
      </SFA>
      <SFA>
        <FILEPATH>C:\Users\b1213\c++\HakuensaiLauncher\</FILEPATH>
        <FILENAME>Game.cpp</FILENAME>
        <LINE>262</LINE>
        <COLUMN>5</COLUMN>
      </SFA>
      <SFA>
        <FILEPATH>C:\Users\b1213\c++\HakuensaiLauncher\</FILEPATH>
        <FILENAME>Game.cpp</FILENAME>
        <LINE>263</LINE>
        <COLUMN>12</COLUMN>
      </SFA>
      <SFA>
        <FILEPATH>C:\Users\b1213\c++\HakuensaiLauncher\</FILEPATH>
        <FILENAME>Game.cpp</FILENAME>
        <LINE>264</LINE>
        <COLUMN>5</COLUMN>
      </SFA>
      <SFA>
        <FILEPATH>C:\Users\b1213\c++\HakuensaiLauncher\</FILEPATH>
        <FILENAME>Game.cpp</FILENAME>
        <LINE>265</LINE>
        <COLUMN>12</COLUMN>
      </SFA>
      <SFA>
        <FILEPATH>C:\Users\b1213\c++\HakuensaiLauncher\</FILEPATH>
        <FILENAME>Game.cpp</FILENAME>
        <LINE>266</LINE>
        <COLUMN>5</COLUMN>
      </SFA>
      <SFA>
        <FILEPATH>C:\Users\b1213\c++\HakuensaiLauncher\</FILEPATH>
        <FILENAME>Game.cpp</FILENAME>
        <LINE>267</LINE>
        <COLUMN>12</COLUMN>
      </SFA>
      <SFA>
        <FILEPATH>C:\Users\b1213\c++\HakuensaiLauncher\</FILEPATH>
        <FILENAME>Game.cpp</FILENAME>
        <LINE>268</LINE>
        <COLUMN>18</COLUMN>
      </SFA>
      <SFA>
        <FILEPATH>C:\Users\b1213\c++\HakuensaiLauncher\</FILEPATH>
        <FILENAME>Game.cpp</FILENAME>
        <LINE>269</LINE>
        <COLUMN>12</COLUMN>
      </SFA>
      <SFA>
        <FILEPATH>C:\Users\b1213\c++\HakuensaiLauncher\</FILEPATH>
        <FILENAME>Game.cpp</FILENAME>
        <LINE>270</LINE>
        <COLUMN>6</COLUMN>
      </SFA>
      <SFA>
        <FILEPATH>C:\Users\b1213\c++\HakuensaiLauncher\</FILEPATH>
        <FILENAME>Game.cpp</FILENAME>
        <LINE>271</LINE>
        <COLUMN>12</COLUMN>
      </SFA>
      <SFA>
        <FILEPATH>C:\Users\b1213\c++\HakuensaiLauncher\</FILEPATH>
        <FILENAME>Game.cpp</FILENAME>
        <LINE>272</LINE>
        <COLUMN>13</COLUMN>
      </SFA>
      <SFA>
        <FILEPATH>C:\Users\b1213\c++\HakuensaiLauncher\</FILEPATH>
        <FILENAME>Game.cpp</FILENAME>
        <LINE>273</LINE>
        <COLUMN>12</COLUMN>
      </SFA>
      <SFA>
        <FILEPATH>C:\Users\b1213\c++\HakuensaiLauncher\</FILEPATH>
        <FILENAME>Game.cpp</FILENAME>
        <LINE>274</LINE>
        <COLUMN>8</COLUMN>
      </SFA>
      <SFA>
        <FILEPATH>C:\Users\b1213\c++\HakuensaiLauncher\</FILEPATH>
        <FILENAME>Game.cpp</FILENAME>
        <LINE>275</LINE>
        <COLUMN>19</COLUMN>
      </SFA>
      <SFA>
        <FILEPATH>C:\Users\b1213\c++\HakuensaiLauncher\</FILEPATH>
        <FILENAME>Game.cpp</FILENAME>
        <LINE>276</LINE>
        <COLUMN>11</COLUMN>
      </SFA>
      <SFA>
        <FILEPATH>C:\Users\b1213\c++\HakuensaiLauncher\</FILEPATH>
        <FILENAME>Game.cpp</FILENAME>
        <LINE>277</LINE>
        <COLUMN>12</COLUMN>
      </SFA>
      <SFA>
        <FILEPATH>C:\Users\b1213\c++\HakuensaiLauncher\</FILEPATH>
        <FILENAME>Game.cpp</FILENAME>
        <LINE>278</LINE>
        <COLUMN>35</COLUMN>
      </SFA>
      <SFA>
        <FILEPATH>C:\Users\b1213\c++\HakuensaiLauncher\</FILEPATH>
        <FILENAME>Game.cpp</FILENAME>
        <LINE>317</LINE>
        <COLUMN>15</COLUMN>
      </SFA>
      <SFA>
        <FILEPATH>C:\Users\b1213\c++\HakuensaiLauncher\</FILEPATH>
        <FILENAME>Game.cpp</FILENAME>
        <LINE>318</LINE>
        <COLUMN>12</COLUMN>
      </SFA>
      <SFA>
        <FILEPATH>C:\Users\b1213\c++\HakuensaiLauncher\</FILEPATH>
        <FILENAME>Game.cpp</FILENAME>
        <LINE>319</LINE>
        <COLUMN>8</COLUMN>
      </SFA>
      <SFA>
        <FILEPATH>C:\Users\b1213\c++\HakuensaiLauncher\</FILEPATH>
        <FILENAME>Game.cpp</FILENAME>
        <LINE>320</LINE>
        <COLUMN>8</COLUMN>
      </SFA>
      <SFA>
        <FILEPATH>C:\Users\b1213\c++\HakuensaiLauncher\</FILEPATH>
        <FILENAME>Game.cpp</FILENAME>
        <LINE>321</LINE>
        <COLUMN>19</COLUMN>
      </SFA>
      <SFA>
        <FILEPATH>C:\Users\b1213\c++\HakuensaiLauncher\</FILEPATH>
        <FILENAME>Game.cpp</FILENAME>
        <LINE>322</LINE>
        <COLUMN>11</COLUMN>
      </SFA>
      <SFA>
        <FILEPATH>C:\Users\b1213\c++\HakuensaiLauncher\</FILEPATH>
        <FILENAME>Game.cpp</FILENAME>
        <LINE>323</LINE>
        <COLUMN>5</COLUMN>
      </SFA>
      <SFA>
        <FILEPATH>C:\Users\b1213\c++\HakuensaiLauncher\</FILEPATH>
        <FILENAME>Game.cpp</FILENAME>
        <LINE>324</LINE>
        <COLUMN>12</COLUMN>
      </SFA>
      <SFA>
        <FILEPATH>C:\Users\b1213\c++\HakuensaiLauncher\</FILEPATH>
        <FILENAME>Game.cpp</FILENAME>
        <LINE>325</LINE>
        <COLUMN>5</COLUMN>
      </SFA>
      <SFA>
        <FILEPATH>C:\Users\b1213\c++\HakuensaiLauncher\</FILEPATH>
        <FILENAME>Game.cpp</FILENAME>
        <LINE>326</LINE>
        <COLUMN>12</COLUMN>
      </SFA>
      <SFA>
        <FILEPATH>C:\Users\b1213\c++\HakuensaiLauncher\</FILEPATH>
        <FILENAME>Game.cpp</FILENAME>
        <LINE>327</LINE>
        <COLUMN>5</COLUMN>
      </SFA>
      <SFA>
        <FILEPATH>C:\Users\b1213\c++\HakuensaiLauncher\</FILEPATH>
        <FILENAME>Game.cpp</FILENAME>
        <LINE>328</LINE>
        <COLUMN>12</COLUMN>
      </SFA>
      <SFA>
        <FILEPATH>C:\Users\b1213\c++\HakuensaiLauncher\</FILEPATH>
        <FILENAME>Game.cpp</FILENAME>
        <LINE>329</LINE>
        <COLUMN>5</COLUMN>
      </SFA>
      <SFA>
        <FILEPATH>C:\Users\b1213\c++\HakuensaiLauncher\</FILEPATH>
        <FILENAME>Game.cpp</FILENAME>
        <LINE>330</LINE>
        <COLUMN>12</COLUMN>
      </SFA>
      <SFA>
        <FILEPATH>C:\Users\b1213\c++\HakuensaiLauncher\</FILEPATH>
        <FILENAME>Game.cpp</FILENAME>
        <LINE>331</LINE>
        <COLUMN>5</COLUMN>
      </SFA>
      <SFA>
        <FILEPATH>C:\Users\b1213\c++\HakuensaiLauncher\</FILEPATH>
        <FILENAME>Game.cpp</FILENAME>
        <LINE>332</LINE>
        <COLUMN>12</COLUMN>
      </SFA>
      <SFA>
        <FILEPATH>C:\Users\b1213\c++\HakuensaiLauncher\</FILEPATH>
        <FILENAME>Game.cpp</FILENAME>
        <LINE>333</LINE>
        <COLUMN>5</COLUMN>
      </SFA>
      <SFA>
        <FILEPATH>C:\Users\b1213\c++\HakuensaiLauncher\</FILEPATH>
        <FILENAME>Game.cpp</FILENAME>
        <LINE>334</LINE>
        <COLUMN>12</COLUMN>
      </SFA>
      <SFA>
        <FILEPATH>C:\Users\b1213\c++\HakuensaiLauncher\</FILEPATH>
        <FILENAME>Game.cpp</FILENAME>
        <LINE>335</LINE>
        <COLUMN>13</COLUMN>
      </SFA>
      <SFA>
        <FILEPATH>C:\Users\b1213\c++\HakuensaiLauncher\</FILEPATH>
        <FILENAME>Game.cpp</FILENAME>
        <LINE>336</LINE>
        <COLUMN>12</COLUMN>
      </SFA>
      <SFA>
        <FILEPATH>C:\Users\b1213\c++\HakuensaiLauncher\</FILEPATH>
        <FILENAME>Game.cpp</FILENAME>
        <LINE>337</LINE>
        <COLUMN>13</COLUMN>
      </SFA>
      <SFA>
        <FILEPATH>C:\Users\b1213\c++\HakuensaiLauncher\</FILEPATH>
        <FILENAME>Game.cpp</FILENAME>
        <LINE>338</LINE>
        <COLUMN>12</COLUMN>
      </SFA>
      <SFA>
        <FILEPATH>C:\Users\b1213\c++\HakuensaiLauncher\</FILEPATH>
        <FILENAME>Game.cpp</FILENAME>
        <LINE>339</LINE>
        <COLUMN>5</COLUMN>
        <KEYEVENT>
          <ID>1</ID>
          <KIND>declaration</KIND>
          <IMPORTANCE>Essential</IMPORTANCE>
          <MESSAGE>'gameeximage' が初期化されていません</MESSAGE>
        </KEYEVENT>
      </SFA>
      <SFA>
        <FILEPATH>C:\Users\b1213\c++\HakuensaiLauncher\</FILEPATH>
        <FILENAME>Game.cpp</FILENAME>
        <LINE>340</LINE>
        <COLUMN>12</COLUMN>
      </SFA>
      <SFA>
        <FILEPATH>C:\Users\b1213\c++\HakuensaiLauncher\</FILEPATH>
        <FILENAME>Game.cpp</FILENAME>
        <LINE>341</LINE>
        <COLUMN>5</COLUMN>
      </SFA>
      <SFA>
        <FILEPATH>C:\Users\b1213\c++\HakuensaiLauncher\</FILEPATH>
        <FILENAME>Game.cpp</FILENAME>
        <LINE>342</LINE>
        <COLUMN>12</COLUMN>
      </SFA>
      <SFA>
        <FILEPATH>C:\Users\b1213\c++\HakuensaiLauncher\</FILEPATH>
        <FILENAME>Game.cpp</FILENAME>
        <LINE>343</LINE>
        <COLUMN>13</COLUMN>
      </SFA>
      <SFA>
        <FILEPATH>C:\Users\b1213\c++\HakuensaiLauncher\</FILEPATH>
        <FILENAME>Game.cpp</FILENAME>
        <LINE>344</LINE>
        <COLUMN>12</COLUMN>
      </SFA>
      <SFA>
        <FILEPATH>C:\Users\b1213\c++\HakuensaiLauncher\</FILEPATH>
        <FILENAME>Game.cpp</FILENAME>
        <LINE>345</LINE>
        <COLUMN>5</COLUMN>
      </SFA>
      <SFA>
        <FILEPATH>C:\Users\b1213\c++\HakuensaiLauncher\</FILEPATH>
        <FILENAME>Game.cpp</FILENAME>
        <LINE>346</LINE>
        <COLUMN>12</COLUMN>
      </SFA>
      <SFA>
        <FILEPATH>C:\Users\b1213\c++\HakuensaiLauncher\</FILEPATH>
        <FILENAME>Game.cpp</FILENAME>
        <LINE>347</LINE>
        <COLUMN>13</COLUMN>
      </SFA>
      <SFA>
        <FILEPATH>C:\Users\b1213\c++\HakuensaiLauncher\</FILEPATH>
        <FILENAME>Game.cpp</FILENAME>
        <LINE>348</LINE>
        <COLUMN>12</COLUMN>
      </SFA>
      <SFA>
        <FILEPATH>C:\Users\b1213\c++\HakuensaiLauncher\</FILEPATH>
        <FILENAME>Game.cpp</FILENAME>
        <LINE>349</LINE>
        <COLUMN>5</COLUMN>
      </SFA>
      <SFA>
        <FILEPATH>C:\Users\b1213\c++\HakuensaiLauncher\</FILEPATH>
        <FILENAME>Game.cpp</FILENAME>
        <LINE>350</LINE>
        <COLUMN>12</COLUMN>
      </SFA>
      <SFA>
        <FILEPATH>C:\Users\b1213\c++\HakuensaiLauncher\</FILEPATH>
        <FILENAME>Game.cpp</FILENAME>
        <LINE>351</LINE>
        <COLUMN>5</COLUMN>
      </SFA>
      <SFA>
        <FILEPATH>C:\Users\b1213\c++\HakuensaiLauncher\</FILEPATH>
        <FILENAME>Game.cpp</FILENAME>
        <LINE>352</LINE>
        <COLUMN>12</COLUMN>
      </SFA>
      <SFA>
        <FILEPATH>C:\Users\b1213\c++\HakuensaiLauncher\</FILEPATH>
        <FILENAME>Game.cpp</FILENAME>
        <LINE>353</LINE>
        <COLUMN>5</COLUMN>
      </SFA>
      <SFA>
        <FILEPATH>C:\Users\b1213\c++\HakuensaiLauncher\</FILEPATH>
        <FILENAME>Game.cpp</FILENAME>
        <LINE>354</LINE>
        <COLUMN>12</COLUMN>
      </SFA>
      <SFA>
        <FILEPATH>C:\Users\b1213\c++\HakuensaiLauncher\</FILEPATH>
        <FILENAME>Game.cpp</FILENAME>
        <LINE>355</LINE>
        <COLUMN>5</COLUMN>
      </SFA>
      <SFA>
        <FILEPATH>C:\Users\b1213\c++\HakuensaiLauncher\</FILEPATH>
        <FILENAME>Game.cpp</FILENAME>
        <LINE>356</LINE>
        <COLUMN>12</COLUMN>
      </SFA>
      <SFA>
        <FILEPATH>C:\Users\b1213\c++\HakuensaiLauncher\</FILEPATH>
        <FILENAME>Game.cpp</FILENAME>
        <LINE>357</LINE>
        <COLUMN>13</COLUMN>
      </SFA>
      <SFA>
        <FILEPATH>C:\Users\b1213\c++\HakuensaiLauncher\</FILEPATH>
        <FILENAME>Game.cpp</FILENAME>
        <LINE>358</LINE>
        <COLUMN>12</COLUMN>
      </SFA>
      <SFA>
        <FILEPATH>C:\Users\b1213\c++\HakuensaiLauncher\</FILEPATH>
        <FILENAME>Game.cpp</FILENAME>
        <LINE>359</LINE>
        <COLUMN>7</COLUMN>
      </SFA>
      <SFA>
        <FILEPATH>C:\Users\b1213\c++\HakuensaiLauncher\</FILEPATH>
        <FILENAME>Game.cpp</FILENAME>
        <LINE>360</LINE>
        <COLUMN>12</COLUMN>
      </SFA>
      <SFA>
        <FILEPATH>C:\Users\b1213\c++\HakuensaiLauncher\</FILEPATH>
        <FILENAME>Game.cpp</FILENAME>
        <LINE>361</LINE>
        <COLUMN>13</COLUMN>
      </SFA>
      <SFA>
        <FILEPATH>C:\Users\b1213\c++\HakuensaiLauncher\</FILEPATH>
        <FILENAME>Game.cpp</FILENAME>
        <LINE>362</LINE>
        <COLUMN>12</COLUMN>
      </SFA>
      <SFA>
        <FILEPATH>C:\Users\b1213\c++\HakuensaiLauncher\</FILEPATH>
        <FILENAME>Game.cpp</FILENAME>
        <LINE>363</LINE>
        <COLUMN>13</COLUMN>
      </SFA>
      <SFA>
        <FILEPATH>C:\Users\b1213\c++\HakuensaiLauncher\</FILEPATH>
        <FILENAME>Game.cpp</FILENAME>
        <LINE>364</LINE>
        <COLUMN>12</COLUMN>
      </SFA>
      <SFA>
        <FILEPATH>C:\Users\b1213\c++\HakuensaiLauncher\</FILEPATH>
        <FILENAME>Game.cpp</FILENAME>
        <LINE>365</LINE>
        <COLUMN>13</COLUMN>
      </SFA>
      <SFA>
        <FILEPATH>C:\Users\b1213\c++\HakuensaiLauncher\</FILEPATH>
        <FILENAME>Game.cpp</FILENAME>
        <LINE>366</LINE>
        <COLUMN>12</COLUMN>
      </SFA>
      <SFA>
        <FILEPATH>C:\Users\b1213\c++\HakuensaiLauncher\</FILEPATH>
        <FILENAME>Game.cpp</FILENAME>
        <LINE>367</LINE>
        <COLUMN>13</COLUMN>
      </SFA>
      <SFA>
        <FILEPATH>C:\Users\b1213\c++\HakuensaiLauncher\</FILEPATH>
        <FILENAME>Game.cpp</FILENAME>
        <LINE>368</LINE>
        <COLUMN>12</COLUMN>
      </SFA>
      <SFA>
        <FILEPATH>C:\Users\b1213\c++\HakuensaiLauncher\</FILEPATH>
        <FILENAME>Game.cpp</FILENAME>
        <LINE>369</LINE>
        <COLUMN>7</COLUMN>
      </SFA>
      <SFA>
        <FILEPATH>C:\Users\b1213\c++\HakuensaiLauncher\</FILEPATH>
        <FILENAME>Game.cpp</FILENAME>
        <LINE>370</LINE>
        <COLUMN>12</COLUMN>
      </SFA>
      <SFA>
        <FILEPATH>C:\Users\b1213\c++\HakuensaiLauncher\</FILEPATH>
        <FILENAME>Game.cpp</FILENAME>
        <LINE>371</LINE>
        <COLUMN>5</COLUMN>
      </SFA>
      <SFA>
        <FILEPATH>C:\Users\b1213\c++\HakuensaiLauncher\</FILEPATH>
        <FILENAME>Game.cpp</FILENAME>
        <LINE>372</LINE>
        <COLUMN>12</COLUMN>
      </SFA>
      <SFA>
        <FILEPATH>C:\Users\b1213\c++\HakuensaiLauncher\</FILEPATH>
        <FILENAME>Game.cpp</FILENAME>
        <LINE>373</LINE>
        <COLUMN>5</COLUMN>
      </SFA>
      <SFA>
        <FILEPATH>C:\Users\b1213\c++\HakuensaiLauncher\</FILEPATH>
        <FILENAME>Game.cpp</FILENAME>
        <LINE>374</LINE>
        <COLUMN>12</COLUMN>
      </SFA>
      <SFA>
        <FILEPATH>C:\Users\b1213\c++\HakuensaiLauncher\</FILEPATH>
        <FILENAME>Game.cpp</FILENAME>
        <LINE>375</LINE>
        <COLUMN>5</COLUMN>
      </SFA>
      <SFA>
        <FILEPATH>C:\Users\b1213\c++\HakuensaiLauncher\</FILEPATH>
        <FILENAME>Game.cpp</FILENAME>
        <LINE>376</LINE>
        <COLUMN>12</COLUMN>
      </SFA>
      <SFA>
        <FILEPATH>C:\Users\b1213\c++\HakuensaiLauncher\</FILEPATH>
        <FILENAME>Game.cpp</FILENAME>
        <LINE>377</LINE>
        <COLUMN>5</COLUMN>
      </SFA>
      <SFA>
        <FILEPATH>C:\Users\b1213\c++\HakuensaiLauncher\</FILEPATH>
        <FILENAME>Game.cpp</FILENAME>
        <LINE>378</LINE>
        <COLUMN>12</COLUMN>
      </SFA>
      <SFA>
        <FILEPATH>C:\Users\b1213\c++\HakuensaiLauncher\</FILEPATH>
        <FILENAME>Game.cpp</FILENAME>
        <LINE>379</LINE>
        <COLUMN>5</COLUMN>
      </SFA>
      <SFA>
        <FILEPATH>C:\Users\b1213\c++\HakuensaiLauncher\</FILEPATH>
        <FILENAME>Game.cpp</FILENAME>
        <LINE>380</LINE>
        <COLUMN>12</COLUMN>
      </SFA>
      <SFA>
        <FILEPATH>C:\Users\b1213\c++\HakuensaiLauncher\</FILEPATH>
        <FILENAME>Game.cpp</FILENAME>
        <LINE>381</LINE>
        <COLUMN>5</COLUMN>
      </SFA>
      <SFA>
        <FILEPATH>C:\Users\b1213\c++\HakuensaiLauncher\</FILEPATH>
        <FILENAME>Game.cpp</FILENAME>
        <LINE>382</LINE>
        <COLUMN>12</COLUMN>
      </SFA>
      <SFA>
        <FILEPATH>C:\Users\b1213\c++\HakuensaiLauncher\</FILEPATH>
        <FILENAME>Game.cpp</FILENAME>
        <LINE>383</LINE>
        <COLUMN>5</COLUMN>
      </SFA>
      <SFA>
        <FILEPATH>C:\Users\b1213\c++\HakuensaiLauncher\</FILEPATH>
        <FILENAME>Game.cpp</FILENAME>
        <LINE>384</LINE>
        <COLUMN>12</COLUMN>
      </SFA>
      <SFA>
        <FILEPATH>C:\Users\b1213\c++\HakuensaiLauncher\</FILEPATH>
        <FILENAME>Game.cpp</FILENAME>
        <LINE>385</LINE>
        <COLUMN>5</COLUMN>
      </SFA>
      <SFA>
        <FILEPATH>C:\Users\b1213\c++\HakuensaiLauncher\</FILEPATH>
        <FILENAME>Game.cpp</FILENAME>
        <LINE>386</LINE>
        <COLUMN>12</COLUMN>
      </SFA>
      <SFA>
        <FILEPATH>C:\Users\b1213\c++\HakuensaiLauncher\</FILEPATH>
        <FILENAME>Game.cpp</FILENAME>
        <LINE>388</LINE>
        <COLUMN>13</COLUMN>
      </SFA>
      <SFA>
        <FILEPATH>C:\Users\b1213\c++\HakuensaiLauncher\</FILEPATH>
        <FILENAME>Game.cpp</FILENAME>
        <LINE>389</LINE>
        <COLUMN>19</COLUMN>
      </SFA>
      <SFA>
        <FILEPATH>C:\Users\b1213\c++\HakuensaiLauncher\</FILEPATH>
        <FILENAME>Game.cpp</FILENAME>
        <LINE>390</LINE>
        <COLUMN>4</COLUMN>
      </SFA>
      <SFA>
        <FILEPATH>C:\Users\b1213\c++\HakuensaiLauncher\</FILEPATH>
        <FILENAME>Game.cpp</FILENAME>
        <LINE>392</LINE>
        <COLUMN>13</COLUMN>
      </SFA>
      <SFA>
        <FILEPATH>C:\Users\b1213\c++\HakuensaiLauncher\</FILEPATH>
        <FILENAME>Game.cpp</FILENAME>
        <LINE>395</LINE>
        <COLUMN>7</COLUMN>
      </SFA>
      <SFA>
        <FILEPATH>C:\Users\b1213\c++\HakuensaiLauncher\</FILEPATH>
        <FILENAME>Game.cpp</FILENAME>
        <LINE>396</LINE>
        <COLUMN>5</COLUMN>
        <KEYEVENT>
          <ID>2</ID>
          <KIND>branch</KIND>
          <IMPORTANCE>Full</IMPORTANCE>
          <MESSAGE>この分岐をスキップする ('curl' が false と仮定)</MESSAGE>
        </KEYEVENT>
      </SFA>
      <SFA>
        <FILEPATH>C:\Users\b1213\c++\HakuensaiLauncher\</FILEPATH>
        <FILENAME>Game.cpp</FILENAME>
        <LINE>416</LINE>
        <COLUMN>12</COLUMN>
      </SFA>
      <SFA>
        <FILEPATH>C:\Users\b1213\c++\HakuensaiLauncher\</FILEPATH>
        <FILENAME>Game.cpp</FILENAME>
        <LINE>417</LINE>
        <COLUMN>14</COLUMN>
        <KEYEVENT>
          <ID>3</ID>
          <KIND>branch</KIND>
          <IMPORTANCE>Full</IMPORTANCE>
          <MESSAGE>この分岐に入る ('gameyouso==0' と仮定)</MESSAGE>
        </KEYEVENT>
      </SFA>
      <SFA>
        <FILEPATH>C:\Users\b1213\c++\HakuensaiLauncher\</FILEPATH>
        <FILENAME>Game.cpp</FILENAME>
        <LINE>418</LINE>
        <COLUMN>13</COLUMN>
      </SFA>
      <SFA>
        <FILEPATH>C:\Users\b1213\c++\HakuensaiLauncher\</FILEPATH>
        <FILENAME>Game.cpp</FILENAME>
        <LINE>419</LINE>
        <COLUMN>12</COLUMN>
      </SFA>
      <SFA>
        <FILEPATH>C:\Users\b1213\c++\HakuensaiLauncher\</FILEPATH>
        <FILENAME>Game.cpp</FILENAME>
        <LINE>421</LINE>
        <COLUMN>12</COLUMN>
      </SFA>
      <SFA>
        <FILEPATH>C:\Users\b1213\c++\HakuensaiLauncher\</FILEPATH>
        <FILENAME>Game.cpp</FILENAME>
        <LINE>421</LINE>
        <COLUMN>39</COLUMN>
      </SFA>
      <SFA>
        <FILEPATH>C:\Users\b1213\c++\HakuensaiLauncher\</FILEPATH>
        <FILENAME>Game.cpp</FILENAME>
        <LINE>421</LINE>
        <COLUMN>12</COLUMN>
      </SFA>
      <SFA>
        <FILEPATH>C:\Users\b1213\c++\HakuensaiLauncher\</FILEPATH>
        <FILENAME>Game.cpp</FILENAME>
        <LINE>421</LINE>
        <COLUMN>32</COLUMN>
      </SFA>
      <SFA>
        <FILEPATH>C:\Users\b1213\c++\HakuensaiLauncher\</FILEPATH>
        <FILENAME>Game.cpp</FILENAME>
        <LINE>421</LINE>
        <COLUMN>12</COLUMN>
      </SFA>
      <SFA>
        <FILEPATH>C:\Users\b1213\c++\HakuensaiLauncher\</FILEPATH>
        <FILENAME>Game.cpp</FILENAME>
        <LINE>421</LINE>
        <COLUMN>60</COLUMN>
      </SFA>
      <SFA>
        <FILEPATH>C:\Users\b1213\c++\HakuensaiLauncher\</FILEPATH>
        <FILENAME>Game.cpp</FILENAME>
        <LINE>421</LINE>
        <COLUMN>12</COLUMN>
      </SFA>
      <SFA>
        <FILEPATH>C:\Users\b1213\c++\HakuensaiLauncher\</FILEPATH>
        <FILENAME>Game.cpp</FILENAME>
        <LINE>422</LINE>
        <COLUMN>12</COLUMN>
      </SFA>
      <SFA>
        <FILEPATH>C:\Users\b1213\c++\HakuensaiLauncher\</FILEPATH>
        <FILENAME>Game.cpp</FILENAME>
        <LINE>422</LINE>
        <COLUMN>42</COLUMN>
      </SFA>
      <SFA>
        <FILEPATH>C:\Users\b1213\c++\HakuensaiLauncher\</FILEPATH>
        <FILENAME>Game.cpp</FILENAME>
        <LINE>422</LINE>
        <COLUMN>12</COLUMN>
      </SFA>
      <SFA>
        <FILEPATH>C:\Users\b1213\c++\HakuensaiLauncher\</FILEPATH>
        <FILENAME>Game.cpp</FILENAME>
        <LINE>422</LINE>
        <COLUMN>35</COLUMN>
      </SFA>
      <SFA>
        <FILEPATH>C:\Users\b1213\c++\HakuensaiLauncher\</FILEPATH>
        <FILENAME>Game.cpp</FILENAME>
        <LINE>422</LINE>
        <COLUMN>12</COLUMN>
      </SFA>
      <SFA>
        <FILEPATH>C:\Users\b1213\c++\HakuensaiLauncher\</FILEPATH>
        <FILENAME>Game.cpp</FILENAME>
        <LINE>422</LINE>
        <COLUMN>63</COLUMN>
      </SFA>
      <SFA>
        <FILEPATH>C:\Users\b1213\c++\HakuensaiLauncher\</FILEPATH>
        <FILENAME>Game.cpp</FILENAME>
        <LINE>422</LINE>
        <COLUMN>12</COLUMN>
      </SFA>
      <SFA>
        <FILEPATH>C:\Users\b1213\c++\HakuensaiLauncher\</FILEPATH>
        <FILENAME>Game.cpp</FILENAME>
        <LINE>423</LINE>
        <COLUMN>12</COLUMN>
      </SFA>
      <SFA>
        <FILEPATH>C:\Users\b1213\c++\HakuensaiLauncher\</FILEPATH>
        <FILENAME>Game.cpp</FILENAME>
        <LINE>423</LINE>
        <COLUMN>34</COLUMN>
      </SFA>
      <SFA>
        <FILEPATH>C:\Users\b1213\c++\HakuensaiLauncher\</FILEPATH>
        <FILENAME>Game.cpp</FILENAME>
        <LINE>423</LINE>
        <COLUMN>12</COLUMN>
      </SFA>
      <SFA>
        <FILEPATH>C:\Users\b1213\c++\HakuensaiLauncher\</FILEPATH>
        <FILENAME>Game.cpp</FILENAME>
        <LINE>423</LINE>
        <COLUMN>27</COLUMN>
      </SFA>
      <SFA>
        <FILEPATH>C:\Users\b1213\c++\HakuensaiLauncher\</FILEPATH>
        <FILENAME>Game.cpp</FILENAME>
        <LINE>423</LINE>
        <COLUMN>12</COLUMN>
      </SFA>
      <SFA>
        <FILEPATH>C:\Users\b1213\c++\HakuensaiLauncher\</FILEPATH>
        <FILENAME>Game.cpp</FILENAME>
        <LINE>423</LINE>
        <COLUMN>55</COLUMN>
      </SFA>
      <SFA>
        <FILEPATH>C:\Users\b1213\c++\HakuensaiLauncher\</FILEPATH>
        <FILENAME>Game.cpp</FILENAME>
        <LINE>423</LINE>
        <COLUMN>12</COLUMN>
      </SFA>
      <SFA>
        <FILEPATH>C:\Users\b1213\c++\HakuensaiLauncher\</FILEPATH>
        <FILENAME>Game.cpp</FILENAME>
        <LINE>424</LINE>
        <COLUMN>1</COLUMN>
      </SFA>
      <SFA>
        <FILEPATH>C:\Users\b1213\c++\HakuensaiLauncher\</FILEPATH>
        <FILENAME>Game.cpp</FILENAME>
        <LINE>425</LINE>
        <COLUMN>13</COLUMN>
      </SFA>
      <SFA>
        <FILEPATH>C:\Users\b1213\c++\HakuensaiLauncher\</FILEPATH>
        <FILENAME>Game.cpp</FILENAME>
        <LINE>425</LINE>
        <COLUMN>27</COLUMN>
      </SFA>
      <SFA>
        <FILEPATH>C:\Users\b1213\c++\HakuensaiLauncher\</FILEPATH>
        <FILENAME>Game.cpp</FILENAME>
        <LINE>426</LINE>
        <COLUMN>17</COLUMN>
      </SFA>
      <SFA>
        <FILEPATH>C:\Users\b1213\c++\HakuensaiLauncher\</FILEPATH>
        <FILENAME>Game.cpp</FILENAME>
        <LINE>427</LINE>
        <COLUMN>11</COLUMN>
      </SFA>
      <SFA>
        <FILEPATH>C:\Users\b1213\c++\HakuensaiLauncher\</FILEPATH>
        <FILENAME>Game.cpp</FILENAME>
        <LINE>428</LINE>
        <COLUMN>18</COLUMN>
      </SFA>
      <SFA>
        <FILEPATH>C:\Users\b1213\c++\HakuensaiLauncher\</FILEPATH>
        <FILENAME>Game.cpp</FILENAME>
        <LINE>429</LINE>
        <COLUMN>9</COLUMN>
      </SFA>
      <SFA>
        <FILEPATH>C:\Users\b1213\c++\HakuensaiLauncher\</FILEPATH>
        <FILENAME>Game.cpp</FILENAME>
        <LINE>430</LINE>
        <COLUMN>18</COLUMN>
      </SFA>
      <SFA>
        <FILEPATH>C:\Users\b1213\c++\HakuensaiLauncher\</FILEPATH>
        <FILENAME>Game.cpp</FILENAME>
        <LINE>431</LINE>
        <COLUMN>12</COLUMN>
      </SFA>
      <SFA>
        <FILEPATH>C:\Users\b1213\c++\HakuensaiLauncher\</FILEPATH>
        <FILENAME>Game.cpp</FILENAME>
        <LINE>432</LINE>
        <COLUMN>16</COLUMN>
      </SFA>
      <SFA>
        <FILEPATH>C:\Users\b1213\c++\HakuensaiLauncher\</FILEPATH>
        <FILENAME>Game.cpp</FILENAME>
        <LINE>425</LINE>
        <COLUMN>34</COLUMN>
      </SFA>
      <SFA>
        <FILEPATH>C:\Users\b1213\c++\HakuensaiLauncher\</FILEPATH>
        <FILENAME>Game.cpp</FILENAME>
        <LINE>425</LINE>
        <COLUMN>27</COLUMN>
      </SFA>
      <SFA>
        <FILEPATH>C:\Users\b1213\c++\HakuensaiLauncher\</FILEPATH>
        <FILENAME>Game.cpp</FILENAME>
        <LINE>426</LINE>
        <COLUMN>17</COLUMN>
      </SFA>
      <SFA>
        <FILEPATH>C:\Users\b1213\c++\HakuensaiLauncher\</FILEPATH>
        <FILENAME>Game.cpp</FILENAME>
        <LINE>427</LINE>
        <COLUMN>11</COLUMN>
      </SFA>
      <SFA>
        <FILEPATH>C:\Users\b1213\c++\HakuensaiLauncher\</FILEPATH>
        <FILENAME>Game.cpp</FILENAME>
        <LINE>428</LINE>
        <COLUMN>18</COLUMN>
      </SFA>
      <SFA>
        <FILEPATH>C:\Users\b1213\c++\HakuensaiLauncher\</FILEPATH>
        <FILENAME>Game.cpp</FILENAME>
        <LINE>429</LINE>
        <COLUMN>9</COLUMN>
      </SFA>
      <SFA>
        <FILEPATH>C:\Users\b1213\c++\HakuensaiLauncher\</FILEPATH>
        <FILENAME>Game.cpp</FILENAME>
        <LINE>430</LINE>
        <COLUMN>18</COLUMN>
      </SFA>
      <SFA>
        <FILEPATH>C:\Users\b1213\c++\HakuensaiLauncher\</FILEPATH>
        <FILENAME>Game.cpp</FILENAME>
        <LINE>431</LINE>
        <COLUMN>12</COLUMN>
      </SFA>
      <SFA>
        <FILEPATH>C:\Users\b1213\c++\HakuensaiLauncher\</FILEPATH>
        <FILENAME>Game.cpp</FILENAME>
        <LINE>432</LINE>
        <COLUMN>16</COLUMN>
      </SFA>
      <SFA>
        <FILEPATH>C:\Users\b1213\c++\HakuensaiLauncher\</FILEPATH>
        <FILENAME>Game.cpp</FILENAME>
        <LINE>425</LINE>
        <COLUMN>34</COLUMN>
      </SFA>
      <SFA>
        <FILEPATH>C:\Users\b1213\c++\HakuensaiLauncher\</FILEPATH>
        <FILENAME>Game.cpp</FILENAME>
        <LINE>425</LINE>
        <COLUMN>27</COLUMN>
      </SFA>
      <SFA>
        <FILEPATH>C:\Users\b1213\c++\HakuensaiLauncher\</FILEPATH>
        <FILENAME>Game.cpp</FILENAME>
        <LINE>434</LINE>
        <COLUMN>30</COLUMN>
        <KEYEVENT>
          <ID>4</ID>
          <KIND>branch</KIND>
          <IMPORTANCE>Full</IMPORTANCE>
          <MESSAGE>このループに入る ('&lt;分岐条件&gt;' と仮定)</MESSAGE>
        </KEYEVENT>
      </SFA>
      <SFA>
        <FILEPATH>C:\Users\b1213\c++\HakuensaiLauncher\</FILEPATH>
        <FILENAME>Game.cpp</FILENAME>
        <LINE>435</LINE>
        <COLUMN>61</COLUMN>
        <KEYEVENT>
          <ID>5</ID>
          <KIND>branch</KIND>
          <IMPORTANCE>Full</IMPORTANCE>
          <MESSAGE>この分岐をスキップする ('&lt;分岐条件&gt;' が false と仮定)</MESSAGE>
        </KEYEVENT>
      </SFA>
      <SFA>
        <FILEPATH>C:\Users\b1213\c++\HakuensaiLauncher\</FILEPATH>
        <FILENAME>Game.cpp</FILENAME>
        <LINE>478</LINE>
        <COLUMN>16</COLUMN>
        <KEYEVENT>
          <ID>6</ID>
          <KIND>branch</KIND>
          <IMPORTANCE>Full</IMPORTANCE>
          <MESSAGE>この分岐をスキップする ('CheckHitKey((65))' が false と仮定)</MESSAGE>
        </KEYEVENT>
      </SFA>
      <SFA>
        <FILEPATH>C:\Users\b1213\c++\HakuensaiLauncher\</FILEPATH>
        <FILENAME>Game.cpp</FILENAME>
        <LINE>491</LINE>
        <COLUMN>17</COLUMN>
        <KEYEVENT>
          <ID>7</ID>
          <KIND>branch</KIND>
          <IMPORTANCE>Full</IMPORTANCE>
          <MESSAGE>この分岐をスキップする ('CheckHitKey((67))' が false と仮定)</MESSAGE>
        </KEYEVENT>
      </SFA>
      <SFA>
        <FILEPATH>C:\Users\b1213\c++\HakuensaiLauncher\</FILEPATH>
        <FILENAME>Game.cpp</FILENAME>
        <LINE>494</LINE>
        <COLUMN>17</COLUMN>
        <KEYEVENT>
          <ID>8</ID>
          <KIND>branch</KIND>
          <IMPORTANCE>Full</IMPORTANCE>
          <MESSAGE>この分岐をスキップする ('CheckHitKey((63))' が false と仮定)</MESSAGE>
        </KEYEVENT>
      </SFA>
      <SFA>
        <FILEPATH>C:\Users\b1213\c++\HakuensaiLauncher\</FILEPATH>
        <FILENAME>Game.cpp</FILENAME>
        <LINE>529</LINE>
        <COLUMN>16</COLUMN>
        <KEYEVENT>
          <ID>9</ID>
          <KIND>branch</KIND>
          <IMPORTANCE>Full</IMPORTANCE>
          <MESSAGE>この分岐をスキップする ('timerinfo==1' が false と仮定)</MESSAGE>
        </KEYEVENT>
      </SFA>
      <SFA>
        <FILEPATH>C:\Users\b1213\c++\HakuensaiLauncher\</FILEPATH>
        <FILENAME>Game.cpp</FILENAME>
        <LINE>549</LINE>
        <COLUMN>17</COLUMN>
        <KEYEVENT>
          <ID>10</ID>
          <KIND>branch</KIND>
          <IMPORTANCE>Full</IMPORTANCE>
          <MESSAGE>この分岐をスキップする ('CheckHitKey((199))' が false と仮定)</MESSAGE>
        </KEYEVENT>
      </SFA>
      <SFA>
        <FILEPATH>C:\Users\b1213\c++\HakuensaiLauncher\</FILEPATH>
        <FILENAME>Game.cpp</FILENAME>
        <LINE>584</LINE>
        <COLUMN>17</COLUMN>
        <KEYEVENT>
          <ID>11</ID>
          <KIND>branch</KIND>
          <IMPORTANCE>Full</IMPORTANCE>
          <MESSAGE>この分岐をスキップする ('CheckHitKey((207))' が false と仮定)</MESSAGE>
        </KEYEVENT>
      </SFA>
      <SFA>
        <FILEPATH>C:\Users\b1213\c++\HakuensaiLauncher\</FILEPATH>
        <FILENAME>Game.cpp</FILENAME>
        <LINE>598</LINE>
        <COLUMN>12</COLUMN>
      </SFA>
      <SFA>
        <FILEPATH>C:\Users\b1213\c++\HakuensaiLauncher\</FILEPATH>
        <FILENAME>Game.cpp</FILENAME>
        <LINE>599</LINE>
        <COLUMN>9</COLUMN>
      </SFA>
      <SFA>
        <FILEPATH>C:\Users\b1213\c++\HakuensaiLauncher\</FILEPATH>
        <FILENAME>Game.cpp</FILENAME>
        <LINE>600</LINE>
        <COLUMN>13</COLUMN>
      </SFA>
      <SFA>
        <FILEPATH>C:\Users\b1213\c++\HakuensaiLauncher\</FILEPATH>
        <FILENAME>Game.cpp</FILENAME>
        <LINE>601</LINE>
        <COLUMN>10</COLUMN>
      </SFA>
      <SFA>
        <FILEPATH>C:\Users\b1213\c++\HakuensaiLauncher\</FILEPATH>
        <FILENAME>Game.cpp</FILENAME>
        <LINE>602</LINE>
        <COLUMN>15</COLUMN>
      </SFA>
      <SFA>
        <FILEPATH>C:\Users\b1213\c++\HakuensaiLauncher\</FILEPATH>
        <FILENAME>Game.cpp</FILENAME>
        <LINE>603</LINE>
        <COLUMN>13</COLUMN>
      </SFA>
      <SFA>
        <FILEPATH>C:\Users\b1213\c++\HakuensaiLauncher\</FILEPATH>
        <FILENAME>Game.cpp</FILENAME>
        <LINE>604</LINE>
        <COLUMN>15</COLUMN>
      </SFA>
      <SFA>
        <FILEPATH>C:\Users\b1213\c++\HakuensaiLauncher\</FILEPATH>
        <FILENAME>Game.cpp</FILENAME>
        <LINE>605</LINE>
        <COLUMN>13</COLUMN>
      </SFA>
      <SFA>
        <FILEPATH>C:\Users\b1213\c++\HakuensaiLauncher\</FILEPATH>
        <FILENAME>Game.cpp</FILENAME>
        <LINE>606</LINE>
        <COLUMN>20</COLUMN>
        <KEYEVENT>
          <ID>12</ID>
          <KIND>branch</KIND>
          <IMPORTANCE>Full</IMPORTANCE>
          <MESSAGE>この分岐に入る ('gametitleinfo==0' と仮定)</MESSAGE>
        </KEYEVENT>
      </SFA>
      <SFA>
        <FILEPATH>C:\Users\b1213\c++\HakuensaiLauncher\</FILEPATH>
        <FILENAME>Game.cpp</FILENAME>
        <LINE>607</LINE>
        <COLUMN>21</COLUMN>
      </SFA>
      <SFA>
        <FILEPATH>C:\Users\b1213\c++\HakuensaiLauncher\</FILEPATH>
        <FILENAME>Game.cpp</FILENAME>
        <LINE>608</LINE>
        <COLUMN>21</COLUMN>
      </SFA>
      <SFA>
        <FILEPATH>C:\Users\b1213\c++\HakuensaiLauncher\</FILEPATH>
        <FILENAME>Game.cpp</FILENAME>
        <LINE>613</LINE>
        <COLUMN>9</COLUMN>
      </SFA>
      <SFA>
        <FILEPATH>C:\Users\b1213\c++\HakuensaiLauncher\</FILEPATH>
        <FILENAME>Game.cpp</FILENAME>
        <LINE>614</LINE>
        <COLUMN>20</COLUMN>
      </SFA>
      <SFA>
        <FILEPATH>C:\Users\b1213\c++\HakuensaiLauncher\</FILEPATH>
        <FILENAME>Game.cpp</FILENAME>
        <LINE>615</LINE>
        <COLUMN>14</COLUMN>
        <KEYEVENT>
          <ID>13</ID>
          <KIND>branch</KIND>
          <IMPORTANCE>Full</IMPORTANCE>
          <MESSAGE>この分岐に入る ('BGMinfo==1' と仮定)</MESSAGE>
        </KEYEVENT>
      </SFA>
      <SFA>
        <FILEPATH>C:\Users\b1213\c++\HakuensaiLauncher\</FILEPATH>
        <FILENAME>Game.cpp</FILENAME>
        <LINE>616</LINE>
        <COLUMN>12</COLUMN>
      </SFA>
      <SFA>
        <FILEPATH>C:\Users\b1213\c++\HakuensaiLauncher\</FILEPATH>
        <FILENAME>Game.cpp</FILENAME>
        <LINE>621</LINE>
        <COLUMN>9</COLUMN>
      </SFA>
      <SFA>
        <FILEPATH>C:\Users\b1213\c++\HakuensaiLauncher\</FILEPATH>
        <FILENAME>Game.cpp</FILENAME>
        <LINE>622</LINE>
        <COLUMN>9</COLUMN>
      </SFA>
      <SFA>
        <FILEPATH>C:\Users\b1213\c++\HakuensaiLauncher\</FILEPATH>
        <FILENAME>Game.cpp</FILENAME>
        <LINE>623</LINE>
        <COLUMN>20</COLUMN>
      </SFA>
      <SFA>
        <FILEPATH>C:\Users\b1213\c++\HakuensaiLauncher\</FILEPATH>
        <FILENAME>Game.cpp</FILENAME>
        <LINE>624</LINE>
        <COLUMN>12</COLUMN>
      </SFA>
      <SFA>
        <FILEPATH>C:\Users\b1213\c++\HakuensaiLauncher\</FILEPATH>
        <FILENAME>Game.cpp</FILENAME>
        <LINE>625</LINE>
        <COLUMN>26</COLUMN>
      </SFA>
      <SFA>
        <FILEPATH>C:\Users\b1213\c++\HakuensaiLauncher\</FILEPATH>
        <FILENAME>Game.cpp</FILENAME>
        <LINE>626</LINE>
        <COLUMN>11</COLUMN>
      </SFA>
      <SFA>
        <FILEPATH>C:\Users\b1213\c++\HakuensaiLauncher\</FILEPATH>
        <FILENAME>Game.cpp</FILENAME>
        <LINE>627</LINE>
        <COLUMN>11</COLUMN>
      </SFA>
      <SFA>
        <FILEPATH>C:\Users\b1213\c++\HakuensaiLauncher\</FILEPATH>
        <FILENAME>Game.cpp</FILENAME>
        <LINE>628</LINE>
        <COLUMN>9</COLUMN>
      </SFA>
      <SFA>
        <FILEPATH>C:\Users\b1213\c++\HakuensaiLauncher\</FILEPATH>
        <FILENAME>Game.cpp</FILENAME>
        <LINE>629</LINE>
        <COLUMN>9</COLUMN>
      </SFA>
      <SFA>
        <FILEPATH>C:\Users\b1213\c++\HakuensaiLauncher\</FILEPATH>
        <FILENAME>Game.cpp</FILENAME>
        <LINE>630</LINE>
        <COLUMN>18</COLUMN>
        <KEYEVENT>
          <ID>14</ID>
          <KIND>branch</KIND>
          <IMPORTANCE>Full</IMPORTANCE>
          <MESSAGE>この分岐をスキップする ('gameexeinfo==1' が false と仮定)</MESSAGE>
        </KEYEVENT>
      </SFA>
      <SFA>
        <FILEPATH>C:\Users\b1213\c++\HakuensaiLauncher\</FILEPATH>
        <FILENAME>Game.cpp</FILENAME>
        <LINE>634</LINE>
        <COLUMN>17</COLUMN>
        <KEYEVENT>
          <ID>15</ID>
          <KIND>branch</KIND>
          <IMPORTANCE>Full</IMPORTANCE>
          <MESSAGE>この分岐をスキップする ('gameexinfo==1' が false と仮定)</MESSAGE>
        </KEYEVENT>
      </SFA>
      <SFA>
        <FILEPATH>C:\Users\b1213\c++\HakuensaiLauncher\</FILEPATH>
        <FILENAME>Game.cpp</FILENAME>
        <LINE>637</LINE>
        <COLUMN>27</COLUMN>
        <KEYEVENT>
          <ID>16</ID>
          <KIND>branch</KIND>
          <IMPORTANCE>Full</IMPORTANCE>
          <MESSAGE>この分岐をスキップする ('&lt;分岐条件&gt;' が false と仮定)</MESSAGE>
        </KEYEVENT>
      </SFA>
      <SFA>
        <FILEPATH>C:\Users\b1213\c++\HakuensaiLauncher\</FILEPATH>
        <FILENAME>Game.cpp</FILENAME>
        <LINE>640</LINE>
        <COLUMN>23</COLUMN>
      </SFA>
      <SFA>
        <FILEPATH>C:\Users\b1213\c++\HakuensaiLauncher\</FILEPATH>
        <FILENAME>Game.cpp</FILENAME>
        <LINE>640</LINE>
        <COLUMN>11</COLUMN>
        <KEYEVENT>
          <ID>17</ID>
          <KIND>usage</KIND>
          <IMPORTANCE>Essential</IMPORTANCE>
          <MESSAGE>'gameeximage' が使用されますが、初期化されていない可能性があります</MESSAGE>
        </KEYEVENT>
      </SFA>
    </PATH>
  </DEFECT>
</DEFECTS>